demapi/__init__.py
demapi/configure/params.py
demapi/configure/payload.py
demapi/configure/view.py
demapi/connector/coroutine.py
demapi/connector/file.py
demapi/connector/sync.py
demapi/exceptions.py
demapi/loader.py
demapi-0.1.6.dist-info/LICENSE
demapi-0.1.6.dist-info/WHEEL
demapi-0.1.6.dist-info/METADATA
demapi-0.1.6.dist-info/RECORD
