Metadata-Version: 2.1
Name: demapi
Version: 0.1.6
Summary: Make customizable demotivators and motivators through imgonline.com.ua API. Supports async-await style
Home-page: https://github.com/deknowny/demapi
License: MIT
Keywords: demotivators,imgonline,async,await,aio
Author: Yan Kurbatov
Author-email: deknowny@gmail.com
Requires-Python: >=3.7,<4.0
Classifier: Framework :: AsyncIO
Classifier: Intended Audience :: Developers
Classifier: License :: OSI Approved :: MIT License
Classifier: Natural Language :: English
Classifier: Programming Language :: Python :: 3
Classifier: Programming Language :: Python :: 3.10
Classifier: Programming Language :: Python :: 3.7
Classifier: Programming Language :: Python :: 3.8
Classifier: Programming Language :: Python :: 3.9
Classifier: Programming Language :: Python :: Implementation :: CPython
Classifier: Programming Language :: Python :: Implementation :: PyPy
Classifier: Topic :: Utilities
Classifier: Typing :: Typed
Provides-Extra: check
Provides-Extra: style
Provides-Extra: test
Requires-Dist: aiohttp (>=3.8.1,<4.0.0)
Requires-Dist: black (>=21.11b1,<22.0); extra == "style"
Requires-Dist: certifi (>=2021.10.8,<2022.0.0)
Requires-Dist: coverage (>=6.1.2,<7.0.0); extra == "test"
Requires-Dist: coveralls (>=3.3.1,<4.0.0); extra == "test"
Requires-Dist: isort (>=5.10.1,<6.0.0); extra == "style"
Requires-Dist: mypy (>=0.910,<0.911); extra == "check"
Requires-Dist: pre-commit (>=2.15.0,<3.0.0); extra == "style"
Requires-Dist: pytest (>=6.2.5,<7.0.0); extra == "test"
Requires-Dist: pytest-asyncio (>=0.16.0,<0.17.0); extra == "test"
Requires-Dist: pytest-cov (>=3.0.0,<4.0.0); extra == "test"
Requires-Dist: requests (>=2.26.0,<3.0.0)
Requires-Dist: types-certifi (>=2021.10.8,<2022.0.0); extra == "check"
Requires-Dist: types-requests (>=2.26.1,<3.0.0); extra == "check"
Project-URL: Documentation, https://github.com/deknowny/demapi/blob/main/GUIDE.md
